airbyte_databricks_cache/__init__.cpython-311-darwin.so
airbyte_databricks_cache/_processors/sql/__init__.cpython-311-darwin.so
airbyte_databricks_cache/_processors/sql/databricks.cpython-311-darwin.so
airbyte_databricks_cache/caches/__init__.cpython-311-darwin.so
airbyte_databricks_cache/caches/databricks.cpython-311-darwin.so
airbyte_databricks_cache-0.1.19.dist-info/METADATA
airbyte_databricks_cache-0.1.19.dist-info/WHEEL
airbyte_databricks_cache-0.1.19.dist-info/RECORD
