Metadata-Version: 2.3
Name: airbyte-databricks-cache
Version: 0.1.19
Summary: 
Author: ossmht
Author-email: ossmht@gmail.com
Requires-Python: >=3.11,<3.12
Classifier: Programming Language :: Python :: 3
Classifier: Programming Language :: Python :: 3.11
Requires-Dist: airbyte (>=0,<1)
Requires-Dist: databricks-sql-connector (>=3.6.0,<4.0.0)
